deepthought_ai/__init__.py
deepthought_ai/main.py
DeepThought_Artificial_Intelligence_AI_Engine_powered_by_AI-0.1.0.dist-info/LICENSE.txt
DeepThought_Artificial_Intelligence_AI_Engine_powered_by_AI-0.1.0.dist-info/METADATA
DeepThought_Artificial_Intelligence_AI_Engine_powered_by_AI-0.1.0.dist-info/WHEEL
DeepThought_Artificial_Intelligence_AI_Engine_powered_by_AI-0.1.0.dist-info/top_level.txt
DeepThought_Artificial_Intelligence_AI_Engine_powered_by_AI-0.1.0.dist-info/RECORD
