Metadata-Version: 2.1
Name: DeepThought-Artificial-Intelligence-AI-Engine-powered-by-AI
Version: 0.1.0
Summary: A Python library for AI-based conditional logic using OpenAI
Home-page: https://github.com/wardbekker/deepthought_ai_framework
Author: Ward Bekker
Author-email: ward@wardbekker.com
Classifier: Programming Language :: Python :: 3
Classifier: License :: OSI Approved :: MIT License
Classifier: Operating System :: OS Independent
Requires-Python: >=3.6
License-File: LICENSE.txt
Requires-Dist: openai >=0.27.0
